LICENSE
gemini_api/__init__.py
gemini_api/authentication.py
gemini_api/endpoints/__init__.py
gemini_api/endpoints/fee_volume.py
gemini_api/endpoints/fund_management.py
gemini_api/endpoints/fx_rate.py
gemini_api/endpoints/order.py
gemini_api/endpoints/public.py
gemini_api/gemini_test.ipynb
gemini_api/utils.py
gemini_api-0.1.5.dist-info/LICENSE
gemini_api-0.1.5.dist-info/WHEEL
gemini_api-0.1.5.dist-info/METADATA
gemini_api-0.1.5.dist-info/RECORD
