Metadata-Version: 2.1
Name: gemini-api
Version: 0.1.5
Summary: A Python wrapper for the Gemini cryptocurrency exchange API
Home-page: https://github.com/eliasbenaddou/gemini_api
License: MIT
Author: Elias Benaddou Idrissi
Requires-Python: >=3.8,<4.0
Classifier: License :: OSI Approved :: MIT License
Classifier: Programming Language :: Python :: 3
Classifier: Programming Language :: Python :: 3.10
Classifier: Programming Language :: Python :: 3.8
Classifier: Programming Language :: Python :: 3.9
Requires-Dist: requests (>=2.28.0,<3.0.0)
Project-URL: Repository, https://github.com/eliasbenaddou/gemini_api
